streng/__init__.py
streng/codes/__init__.py
streng/codes/eurocodes/__init__.py
streng/codes/eurocodes/ec2/__init__.py
streng/codes/eurocodes/ec2/raw/__init__.py
streng/codes/eurocodes/ec2/raw/ch3/__init__.py
streng/codes/eurocodes/ec2/raw/ch3/concrete/__init__.py
streng/codes/eurocodes/ec2/raw/ch3/concrete/elastic_deformation.py
streng/codes/eurocodes/ec2/raw/ch3/concrete/strength.py
streng/codes/eurocodes/ec2/raw/ch3/concrete/stress_strain.py
streng/codes/eurocodes/ec2/raw/ch4/__init__.py
streng/codes/eurocodes/ec2/raw/ch4/concrete_cover.py
streng/codes/eurocodes/ec2/raw/ch5/__init__.py
streng/codes/eurocodes/ec2/raw/ch5/geometric_data/__init__.py
streng/codes/eurocodes/ec2/raw/ch5/geometric_data/effective_width.py
streng/codes/eurocodes/ec2/raw/ch6/__init__.py
streng/codes/eurocodes/ec2/raw/ch6/shear.py
streng/codes/eurocodes/ec8/__init__.py
streng/codes/eurocodes/ec8/cls/__init__.py
streng/codes/eurocodes/ec8/cls/seismic_action/__init__.py
streng/codes/eurocodes/ec8/cls/seismic_action/spectra.py
streng/codes/eurocodes/ec8/raw/__init__.py
streng/codes/eurocodes/ec8/raw/ch3/__init__.py
streng/codes/eurocodes/ec8/raw/ch3/seismic_action/__init__.py
streng/codes/eurocodes/ec8/raw/ch3/seismic_action/spectra.py
streng/codes/eurocodes/ec8/raw/ch5/__init__.py
streng/codes/eurocodes/ec8/raw/ch5/detailing/__init__.py
streng/codes/eurocodes/ec8/raw/ch5/detailing/beams.py
streng/codes/greek/__init__.py
streng/codes/greek/eak2000/__init__.py
streng/codes/greek/eak2000/raw/__init__.py
streng/codes/greek/eak2000/raw/ch2/__init__.py
streng/codes/greek/eak2000/raw/ch2/seismic_action/__init__.py
streng/codes/greek/eak2000/raw/ch2/seismic_action/spectra.py
streng/codes/greek/ekos2000/__init__.py
streng/codes/greek/kanepe/__init__.py
streng/codes/greek/kanepe/assessment/__init__.py
streng/codes/greek/kanepe/assessment/section_properties/__init__.py
streng/codes/greek/kanepe/assessment/section_properties/common.py
streng/codes/greek/kanepe/assessment/section_properties/rectangular.py
streng-0.0.7.dist-info/LICENSE
streng-0.0.7.dist-info/METADATA
streng-0.0.7.dist-info/WHEEL
streng-0.0.7.dist-info/top_level.txt
streng-0.0.7.dist-info/RECORD
