Metadata-Version: 2.1
Name: streng
Version: 0.0.7
Summary: structural engineering tools with python
Home-page: https://github.com/gpanagop/streng
Author: panagop
Author-email: giorgos@panagop.com
License: MIT License        
Platform: UNKNOWN
Classifier: Programming Language :: Python :: 3.7
Classifier: License :: OSI Approved :: MIT License
Classifier: Operating System :: OS Independent
Requires-Python: >=3.7
License-File: LICENSE
Requires-Dist: tabulate
Requires-Dist: numpy
Requires-Dist: matplotlib
Requires-Dist: pandas
Requires-Dist: sympy
Requires-Dist: scipy
Requires-Dist: sqlalchemy
